tkitLogger
