Metadata-Version: 2.1
Name: tkitLogger
Version: 0.0.0.2
Summary: Terry toolkit tkitLogger
Home-page: http://www.terrychan.org/tkitLogger/
Author: Terry Chan
Author-email: napoler2008@gmail.com
License: UNKNOWN
Platform: UNKNOWN
